textnoisr/__init__.py
textnoisr/noise.py
textnoisr/noise_dataset.py
textnoisr/noise_unbiasing.py
textnoisr-1.1.3.dist-info/LICENSE
textnoisr-1.1.3.dist-info/METADATA
textnoisr-1.1.3.dist-info/WHEEL
textnoisr-1.1.3.dist-info/RECORD
