Metadata-Version: 2.3
Name: textnoisr
Version: 1.1.3
Summary: Add noise to text at the character level
License: BSD-2-Clause
Keywords: nlp,natural language processing,text,augmentation,ocr,typo
Author: Lilian Sanselme
Author-email: lilian.sanselme@preligens.com
Maintainer: Félix Martel
Maintainer-email: felix.martel@preligens.com
Requires-Python: >=3.10,<3.13
Classifier: License :: OSI Approved :: BSD License
Classifier: Programming Language :: Python :: 3
Classifier: Programming Language :: Python :: 3.10
Classifier: Programming Language :: Python :: 3.11
Classifier: Programming Language :: Python :: 3.12
Classifier: Topic :: Text Processing :: General
Requires-Dist: datasets (>=2.14.5)
Requires-Dist: numpy (>=1.26.1)
Requires-Dist: scipy (>=1.11.3)
Project-URL: Bug Tracker, https://github.com/preligens-lab/textnoisr/issues
Project-URL: Documentation, https://preligens-lab.github.io/textnoisr
Project-URL: Homepage, https://preligens-lab.github.io/textnoisr
Project-URL: Repository, https://github.com/preligens-lab/textnoisr
